{
  "Built-in": [
    "declare",
    "function",
    "local",
    "popd",
    "pushd",
    "shopt",
    "typeset"
  ],

  "Shell": [
    "ash",
    "bash",
    "csh",
    "dash",
    "ksh",
    "ksh93",
    "tcsh",
    "zsh"
  ],

  "Scripting Language": [
    "perl",
    "python",
    "python2",
    "python3",
    "ruby"
  ],

  "Programming": [
    "seq",
    "units",
    "yes"
  ],

  "Text": [
    "less"
  ],

  "Files": [
    "chroot",
    "cksum",
    "locate",
    "lsof",
    "mktemp",
    "mount",
    "stat",
    "sum",
    "sync",
    "tar",
    "umount",
    "whereis",
    "which"
  ],

  "Processes": [
    "killall",
    "pgrep",
    "pkill"
  ],

  "Development": [
    "git"
  ],

  "Admin": [
    "dmesg",
    "free",
    "reboot",
    "shutdown",
    "su",
    "sudo",
    "uptime"
  ],

  "Terminal": [
    "clear",
    "screen",
    "tmux"
  ],

  "Network": [
    "curl",
    "dig",
    "hostname",
    "ifconfig",
    "mtr",
    "nc",
    "netstat",
    "nslookup",
    "ping",
    "rsync",
    "scp",
    "ssh",
    "wget"
  ],

  "Compression": [
    "bzip2",
    "gzip",
    "zip"
  ],

  "Misc": [
    "history",
    "logout",
    "openssl",
    "watch",
    "whoami",
    "xdg-open"
  ]
}
